pege/__init__.py
pege/constants.py
pege/pege.pt
pege/pege.py
pege/utils.py
pege-1.2.1.dist-info/WHEEL
pege-1.2.1.dist-info/METADATA
pege-1.2.1.dist-info/RECORD
