Metadata-Version: 2.1
Name: pege
Version: 1.2.1
Summary: Protein embeddings to describe local electrostic enviroments
Home-page: https://github.com/bayer-science-for-a-better-life/pege
License: MIT
Author: Pedro Reis
Author-email: pdreis@fc.ul.pt
Requires-Python: >=3.6.2,<4.0
Classifier: Development Status :: 5 - Production/Stable
Classifier: Intended Audience :: Science/Research
Classifier: License :: OSI Approved :: MIT License
Classifier: Programming Language :: Python :: 3
Classifier: Programming Language :: Python :: 3.10
Classifier: Programming Language :: Python :: 3.7
Classifier: Programming Language :: Python :: 3.8
Classifier: Programming Language :: Python :: 3.9
Classifier: Topic :: Scientific/Engineering
Requires-Dist: pandas
Requires-Dist: pdbmender (>=0.5.4,<0.6.0)
Requires-Dist: torch (>=1.9.0)
Project-URL: Repository, https://github.com/bayer-science-for-a-better-life/pege
